haystac/__init__.py
haystac/cli.py
haystac/config/config.yaml
haystac/workflow/workflow.smk
haystac/workflow/envs/adapterremoval.yaml
haystac/workflow/envs/bowtie2.yaml
haystac/workflow/envs/dedup.yaml
haystac/workflow/envs/dirichlet_reads.yaml
haystac/workflow/envs/download_seq.yaml
haystac/workflow/envs/extract_fastq.yaml
haystac/workflow/envs/mapdamage.yaml
haystac/workflow/envs/picard.yaml
haystac/workflow/envs/pysam.yaml
haystac/workflow/envs/samtools.yaml
haystac/workflow/envs/scipy.yaml
haystac/workflow/envs/seqtk.yaml
haystac/workflow/envs/sra_tools.yaml
haystac/workflow/envs/wget.yaml
haystac/workflow/rules/accession_align.smk
haystac/workflow/rules/accession_index.smk
haystac/workflow/rules/adapterremoval.smk
haystac/workflow/rules/database_align.smk
haystac/workflow/rules/database_index.smk
haystac/workflow/rules/entrez.smk
haystac/workflow/rules/entrez_custom_db.smk
haystac/workflow/rules/mapdamage.smk
haystac/workflow/rules/metagenomics.smk
haystac/workflow/rules/refseq.smk
haystac/workflow/rules/sample.smk
haystac/workflow/rules/split_reads.smk
haystac/workflow/rules/sra.smk
haystac/workflow/scripts/calculate_bt2_idx_chunks.py
haystac/workflow/scripts/calculate_dirichlet_abundances.py
haystac/workflow/scripts/calculate_likelihoods.py
haystac/workflow/scripts/calculate_taxa_probabilities.py
haystac/workflow/scripts/concat_files.py
haystac/workflow/scripts/count_accession_ts_tv.py
haystac/workflow/scripts/coverage_stats.py
haystac/workflow/scripts/entrez_db_list.py
haystac/workflow/scripts/entrez_download_sequence.py
haystac/workflow/scripts/entrez_invalid_assemblies.py
haystac/workflow/scripts/entrez_nuccore_query.py
haystac/workflow/scripts/entrez_pick_sequences.py
haystac/workflow/scripts/entrez_refseq_create_files.py
haystac/workflow/scripts/entrez_refseq_eukaryotes_create_files.py
haystac/workflow/scripts/entrez_refseq_virus_create_files.py
haystac/workflow/scripts/entrez_taxonomy_query.py
haystac/workflow/scripts/entrez_utils.py
haystac-0.4.12.dist-info/LICENSE
haystac-0.4.12.dist-info/METADATA
haystac-0.4.12.dist-info/WHEEL
haystac-0.4.12.dist-info/entry_points.txt
haystac-0.4.12.dist-info/top_level.txt
haystac-0.4.12.dist-info/RECORD
