Metadata-Version: 2.1
Name: haystac
Version: 0.4.12
Summary: Species identification pipeline for both single species and metagenomic samples.
Home-page: https://github.com/antonisdim/haystac
Author: Evangelos A. Dimopoulos, Evan K. Irving-Pease
Author-email: antonisdim41@gmail.com
License: MIT
Classifier: Programming Language :: Python :: 3
Classifier: License :: OSI Approved :: MIT License
License-File: LICENSE
Requires-Dist: argparse (~=1.4.0)
Requires-Dist: numpy (~=2.0.0)
Requires-Dist: pandas (~=2.2.2)
Requires-Dist: psutil (~=5.7.2)
Requires-Dist: pyyaml (~=5.4.1)
Requires-Dist: requests (~=2.24.0)
Requires-Dist: setuptools (~=70.1.1)
Requires-Dist: snakemake (~=6.3.0)
